idemlib/__init__.py
idemlib/hashers.py
idemlib-0.1.7.dist-info/METADATA
idemlib-0.1.7.dist-info/WHEEL
idemlib-0.1.7.dist-info/top_level.txt
idemlib-0.1.7.dist-info/RECORD
